replicators/__init__.py
replicators/multiprocess.py
replicators-1.2.1.dist-info/LICENSE
replicators-1.2.1.dist-info/METADATA
replicators-1.2.1.dist-info/WHEEL
replicators-1.2.1.dist-info/entry_points.txt
replicators-1.2.1.dist-info/top_level.txt
replicators-1.2.1.dist-info/RECORD
