Metadata-Version: 2.1
Name: replicators
Version: 1.2.1
Summary: abstraction for concurrency and multithreading
Home-page: https://github.com/bclipp/replicators
Author: Brian Lipp
Author-email: bclipp770@gmail.com
License: MIT
Platform: UNKNOWN
Classifier: License :: OSI Approved :: MIT License
Classifier: Programming Language :: Python
Classifier: Programming Language :: Python :: 3
